{
  "Ramp": {
    "height_bottom": 137.0,
    "height_top": 137.0,
    "width_bottom": 20.0,
    "width_top": 20.0,
    "material": "Opacity80",
    "is_timer_enabled": false,
    "timer_interval": 100,
    "ramp_type": "flat",
    "name": "Ramp7",
    "image": "",
    "image_alignment": "wrap",
    "image_walls": true,
    "left_wall_height": 62.0,
    "right_wall_height": 62.0,
    "left_wall_height_visible": 0.0,
    "right_wall_height_visible": 0.0,
    "hit_event": false,
    "threshold": 2.0,
    "elasticity": 0.3,
    "friction": 0.025,
    "scatter": 0.0,
    "is_collidable": false,
    "is_visible": true,
    "depth_bias": 0.0,
    "wire_diameter": 8.0,
    "wire_distance_x": 38.0,
    "wire_distance_y": 88.0,
    "is_reflection_enabled": true,
    "physics_material": "",
    "overwrite_physics": true,
    "drag_points": [
      {
        "x": 662.78534,
        "y": 934.94946,
        "z": -85.0,
        "smooth": false,
        "is_slingshot": false,
        "has_auto_texture": true,
        "tex_coord": 0.0,
        "is_locked": false,
        "editor_layer": 0,
        "editor_layer_name": "",
        "editor_layer_visibility": true
      },
      {
        "x": 762.8234,
        "y": 780.52454,
        "z": 0.0,
        "smooth": true,
        "is_slingshot": false,
        "has_auto_texture": true,
        "tex_coord": 0.0,
        "is_locked": false,
        "editor_layer": 0,
        "editor_layer_name": "",
        "editor_layer_visibility": true
      },
      {
        "x": 824.9654,
        "y": 563.7376,
        "z": 0.0,
        "smooth": true,
        "is_slingshot": false,
        "has_auto_texture": true,
        "tex_coord": 0.0,
        "is_locked": false,
        "editor_layer": 0,
        "editor_layer_name": "",
        "editor_layer_visibility": true
      },
      {
        "x": 792.34296,
        "y": 328.48877,
        "z": 0.0,
        "smooth": true,
        "is_slingshot": false,
        "has_auto_texture": true,
        "tex_coord": 0.0,
        "is_locked": false,
        "editor_layer": 0,
        "editor_layer_name": "",
        "editor_layer_visibility": true
      },
      {
        "x": 653.50397,
        "y": 211.98586,
        "z": 0.0,
        "smooth": true,
        "is_slingshot": false,
        "has_auto_texture": true,
        "tex_coord": 0.0,
        "is_locked": false,
        "editor_layer": 0,
        "editor_layer_name": "",
        "editor_layer_visibility": true
      },
      {
        "x": 438.0,
        "y": 199.2328,
        "z": 0.0,
        "smooth": false,
        "is_slingshot": false,
        "has_auto_texture": true,
        "tex_coord": 0.0,
        "is_locked": false,
        "editor_layer": 0,
        "editor_layer_name": "",
        "editor_layer_visibility": true
      }
    ]
  }
}