{
  "Rubber": {
    "height": 31.0,
    "hit_height": 27.0,
    "thickness": 8,
    "hit_event": true,
    "material": "Rubber White",
    "is_timer_enabled": false,
    "timer_interval": 100,
    "name": "Rubber21",
    "image": "",
    "elasticity": 0.8,
    "elasticity_falloff": 0.4,
    "friction": 0.6,
    "scatter": 5.0,
    "is_collidable": true,
    "is_visible": true,
    "radb": null,
    "static_rendering": true,
    "show_in_editor": false,
    "rot_x": 0.0,
    "rot_y": 0.0,
    "rot_z": 0.0,
    "is_reflection_enabled": true,
    "physics_material": "a_physics_Rubbers",
    "overwrite_physics": false,
    "drag_points": [
      {
        "x": 301.90237,
        "y": 297.8381,
        "z": 0.0,
        "smooth": true,
        "is_slingshot": false,
        "has_auto_texture": true,
        "tex_coord": 0.0,
        "is_locked": false,
        "editor_layer": 0,
        "editor_layer_name": "",
        "editor_layer_visibility": true
      },
      {
        "x": 291.72,
        "y": 302.05576,
        "z": 0.0,
        "smooth": true,
        "is_slingshot": false,
        "has_auto_texture": true,
        "tex_coord": 0.0,
        "is_locked": false,
        "editor_layer": 0,
        "editor_layer_name": "",
        "editor_layer_visibility": true
      },
      {
        "x": 287.50235,
        "y": 312.23813,
        "z": 0.0,
        "smooth": true,
        "is_slingshot": false,
        "has_auto_texture": true,
        "tex_coord": 0.0,
        "is_locked": false,
        "editor_layer": 0,
        "editor_layer_name": "",
        "editor_layer_visibility": true
      },
      {
        "x": 291.72,
        "y": 322.4205,
        "z": 0.0,
        "smooth": true,
        "is_slingshot": false,
        "has_auto_texture": true,
        "tex_coord": 0.0,
        "is_locked": false,
        "editor_layer": 0,
        "editor_layer_name": "",
        "editor_layer_visibility": true
      },
      {
        "x": 301.90237,
        "y": 326.63815,
        "z": 0.0,
        "smooth": true,
        "is_slingshot": false,
        "has_auto_texture": true,
        "tex_coord": 0.0,
        "is_locked": false,
        "editor_layer": 0,
        "editor_layer_name": "",
        "editor_layer_visibility": true
      },
      {
        "x": 312.08475,
        "y": 322.4205,
        "z": 0.0,
        "smooth": true,
        "is_slingshot": false,
        "has_auto_texture": true,
        "tex_coord": 0.0,
        "is_locked": false,
        "editor_layer": 0,
        "editor_layer_name": "",
        "editor_layer_visibility": true
      },
      {
        "x": 316.3024,
        "y": 312.23813,
        "z": 0.0,
        "smooth": true,
        "is_slingshot": false,
        "has_auto_texture": true,
        "tex_coord": 0.0,
        "is_locked": false,
        "editor_layer": 0,
        "editor_layer_name": "",
        "editor_layer_visibility": true
      },
      {
        "x": 312.08475,
        "y": 302.05576,
        "z": 0.0,
        "smooth": true,
        "is_slingshot": false,
        "has_auto_texture": true,
        "tex_coord": 0.0,
        "is_locked": false,
        "editor_layer": 0,
        "editor_layer_name": "",
        "editor_layer_visibility": true
      }
    ]
  }
}